opinions/__init__.py
opinions/cli.py
opinions/opinion_mypy.py
opinions/opinion_pep517.py
opinions/opinion_poetry_dynamic_version.py
opinions/opinion_poetry_sources.py
opinions/opinion_ruff.py
opinions/opinion_ruff_vscode.py
opinions/pytest_self_check.py
opinions-2.0.0.dist-info/LICENSE
opinions-2.0.0.dist-info/METADATA
opinions-2.0.0.dist-info/WHEEL
opinions-2.0.0.dist-info/entry_points.txt
opinions-2.0.0.dist-info/RECORD
