Metadata-Version: 2.1
Name: opinions
Version: 2.0.0
Summary: The correct way to configure your project
License: Apache-2.0
Author: William Hughes
Author-email: will@willhughes.name
Requires-Python: >=3.10,<4
Classifier: License :: OSI Approved :: Apache Software License
Classifier: Programming Language :: Python :: 3
Classifier: Programming Language :: Python :: 3.10
Classifier: Programming Language :: Python :: 3.11
Classifier: Programming Language :: Python :: 3.12
Classifier: Programming Language :: Python :: 3.13
Requires-Dist: build (>=1.2.1,<2.0.0)
Requires-Dist: mypy (>=1.13.0,<2.0.0)
Requires-Dist: poethepoet (>=0.26.1,<0.27.0)
Requires-Dist: poetry-dynamic-versioning (>=1.4.0,<2.0.0)
Requires-Dist: pytest (>=8.3.4,<9.0.0)
Requires-Dist: pytest-mypy (>=0.10.3,<0.11.0)
Requires-Dist: pytest-ruff (>=0.4.1,<0.5.0)
Requires-Dist: ruff (>=0.8.2,<0.9.0)
Requires-Dist: tomlkit (>=0.12.3,<0.13.0)
